{"11001":{"id":11001,"name":"木剑","describe":"木剑,攻击在4-4之间","more_info":null,"gold":10},"11002":{"id":11002,"name":"铁剑","describe":"铁剑,攻击在8-12之间","more_info":null,"gold":150},"11003":{"id":11003,"name":"淬火青铜剑","describe":"淬火青铜剑,攻击在15-18之间","more_info":null,"gold":450},"11004":{"id":11004,"name":"钢纹宽刃剑","describe":"钢纹宽刃剑,攻击在22-28之间","more_info":null,"gold":1200},"11005":{"id":11005,"name":"银蚀破魔剑","describe":"银蚀破魔剑,攻击在30-38之间","more_info":null,"gold":2800},"11006":{"id":11006,"name":"熔岩焰锋剑","describe":"熔岩焰锋剑,攻击在35-45之间","more_info":null,"gold":6500},"11007":{"id":11007,"name":"寒霜裁决者","describe":"寒霜裁决者,攻击在40-50之间","more_info":null,"gold":9000},"11008":{"id":11008,"name":"秘银圣灵剑","describe":"秘银圣灵剑,攻击在55-65之间","more_info":null,"gold":18000},"11009":{"id":11009,"name":"龙血诅咒刃","describe":"龙血诅咒刃,攻击在70-85之间","more_info":null,"gold":35000},"11010":{"id":11010,"name":"诸神黄昏","describe":"诸神黄昏,攻击在95-120之间","more_info":null,"gold":75000}}